dream_evaluator/Evaluator.py
dream_evaluator/Recorder.py
dream_evaluator/__init__.py
dream_evaluator/utils.py
dream_evaluator-0.1.2.dist-info/licenses/LICENSE
dream_evaluator-0.1.2.dist-info/METADATA
dream_evaluator-0.1.2.dist-info/WHEEL
dream_evaluator-0.1.2.dist-info/top_level.txt
dream_evaluator-0.1.2.dist-info/RECORD
