Metadata-Version: 2.4
Name: dream_evaluator
Version: 0.1.2
Summary: A concise and efficient evaluation framework
Author-email: MZ chen <hyhpchenmengzhu@gmail.com>
License-Expression: MIT
Project-URL: Homepage, https://github.com/VMIJUNV/evaluator
Requires-Python: >=3.8
License-File: LICENSE
Dynamic: license-file
